test/__init__.py
test/entities/__init__.py
test/entities/test_XDCCPack.py
xdcc_dl/__init__.py
xdcc_dl/helper.py
xdcc_dl/entities/IrcServer.py
xdcc_dl/entities/User.py
xdcc_dl/entities/XDCCPack.py
xdcc_dl/entities/__init__.py
xdcc_dl/pack_search/SearchEngine.py
xdcc_dl/pack_search/__init__.py
xdcc_dl/pack_search/procedures/__init__.py
xdcc_dl/pack_search/procedures/ixirc.py
xdcc_dl/pack_search/procedures/nibl.py
xdcc_dl/pack_search/procedures/subsplease.py
xdcc_dl/pack_search/procedures/xdcc_eu.py
xdcc_dl/xdcc/XDCCClient.py
xdcc_dl/xdcc/__init__.py
xdcc_dl/xdcc/exceptions.py
xdcc_dl-5.2.1.data/scripts/xdcc-browse
xdcc_dl-5.2.1.data/scripts/xdcc-dl
xdcc_dl-5.2.1.data/scripts/xdcc-search
xdcc_dl-5.2.1.dist-info/LICENSE
xdcc_dl-5.2.1.dist-info/METADATA
xdcc_dl-5.2.1.dist-info/WHEEL
xdcc_dl-5.2.1.dist-info/top_level.txt
xdcc_dl-5.2.1.dist-info/RECORD
