Metadata-Version: 2.1
Name: xdcc-dl
Version: 5.2.1
Summary: An XDCC File Downloader based on the irclib framework
Home-page: https://gitlab.namibsun.net/namibsun/python/xdcc-dl
Author: Hermann Krumrey
Author-email: hermann@krumreyh.com
License: GNU GPL3
Platform: UNKNOWN
Classifier: License :: OSI Approved :: GNU General Public License v3 (GPLv3)
License-File: LICENSE
Requires-Dist: bs4
Requires-Dist: requests
Requires-Dist: cfscrape
Requires-Dist: typing
Requires-Dist: colorama
Requires-Dist: irc
Requires-Dist: puffotter
Requires-Dist: sentry-sdk
Requires-Dist: names
